pywddff/__init__.py
pywddff/coefs.py
pywddff/data/__init__.py
pywddff/data/camels_subset.pkl
pywddff/data/scaling_dict.pkl
pywddff/data/wavelet_dict.pkl
pywddff/datasets.py
pywddff/filters.py
pywddff/pywddff.py
pywddff/utils.py
pywddff-0.1.0.dist-info/LICENSE
pywddff-0.1.0.dist-info/METADATA
pywddff-0.1.0.dist-info/WHEEL
pywddff-0.1.0.dist-info/RECORD
