Metadata-Version: 2.1
Name: pywddff
Version: 0.1.0
Summary: Python package to perform feature engineering using wavelet transforms, geared towards those who work with tabular data and machine learning models to forecast time series.
License: MIT
Author: John You
Requires-Python: >=3.9
Classifier: License :: OSI Approved :: MIT License
Classifier: Programming Language :: Python :: 3
Classifier: Programming Language :: Python :: 3.9
Classifier: Programming Language :: Python :: 3.10
Classifier: Programming Language :: Python :: 3.11
Requires-Dist: numpy (>=1.24.2)
Requires-Dist: pandas (>=1.5.3)
